ISReader/Reader.py
ISReader/__init__.py
ISReader/configutil.py
ISReader/version.py
ISReader-1.0.0.dist-info/METADATA
ISReader-1.0.0.dist-info/WHEEL
ISReader-1.0.0.dist-info/top_level.txt
ISReader-1.0.0.dist-info/RECORD
